pyce3.py
pyce3-1.0.0.dist-info/LICENSE
pyce3-1.0.0.dist-info/METADATA
pyce3-1.0.0.dist-info/WHEEL
pyce3-1.0.0.dist-info/top_level.txt
pyce3-1.0.0.dist-info/RECORD
