Metadata-Version: 2.1
Name: pyce3
Version: 1.0.0
Summary: Multilingual Web Page Content Extractor
Home-page: https://github.com/liuzl/pyce3
Author: Zhanliang Liu
Author-email: liang@zliu.org
License: UNKNOWN
Platform: UNKNOWN
Classifier: Programming Language :: Python :: 3
Classifier: License :: OSI Approved :: Apache Software License
Classifier: Operating System :: OS Independent
Requires-Python: >=3.6
Requires-Dist: chardet
Requires-Dist: python-dateutil
Requires-Dist: lxml
